enoceanx/__init__.py
enoceanx/consolelogger.py
enoceanx/decorators.py
enoceanx/utils.py
enoceanx/__pycache__/__init__.cpython-39.pyc
enoceanx/communicators/__init__.py
enoceanx/communicators/communicator.py
enoceanx/communicators/serialcommunicator.py
enoceanx/communicators/tcpcommunicator.py
enoceanx/communicators/utils.py
enoceanx/protocol/EEP.xml
enoceanx/protocol/__init__.py
enoceanx/protocol/common_command_codes.py
enoceanx/protocol/constants.py
enoceanx/protocol/crc8.py
enoceanx/protocol/eep.py
enoceanx/protocol/packet.py
enoceanx/protocol/smart_ack_command_codes.py
enoceanx/protocol/teachin.py
enoceanx/protocol/__pycache__/__init__.cpython-39.pyc
enoceanx/protocol/__pycache__/packet.cpython-39.pyc
enoceanx-0.63.data/scripts/enocean_example.py
enoceanx-0.63.dist-info/LICENSE
enoceanx-0.63.dist-info/METADATA
enoceanx-0.63.dist-info/WHEEL
enoceanx-0.63.dist-info/top_level.txt
enoceanx-0.63.dist-info/RECORD
